pluginmanager/__init__.py
pluginmanager/compat.py
pluginmanager/directory_manager.py
pluginmanager/entry_point_manager.py
pluginmanager/file_manager.py
pluginmanager/iplugin.py
pluginmanager/module_manager.py
pluginmanager/plugin_interface.py
pluginmanager/plugin_manager.py
pluginmanager/util.py
pluginmanager/file_filters/__init__.py
pluginmanager/file_filters/_forbidden_name.py
pluginmanager/file_filters/filenames.py
pluginmanager/file_filters/matching_regex.py
pluginmanager/file_filters/with_info_file.py
pluginmanager/module_filters/__init__.py
pluginmanager/module_filters/keyword_parser.py
pluginmanager/module_filters/subclass_parser.py
pluginmanager/plugin_filters/__init__.py
pluginmanager/plugin_filters/active.py
pluginmanager/plugin_filters/by_name.py
pluginmanager-0.4.1.dist-info/DESCRIPTION.rst
pluginmanager-0.4.1.dist-info/METADATA
pluginmanager-0.4.1.dist-info/RECORD
pluginmanager-0.4.1.dist-info/WHEEL
pluginmanager-0.4.1.dist-info/metadata.json
pluginmanager-0.4.1.dist-info/top_level.txt
